[
    {
        "\u6700\u9ad8\u8840\u5727\uff08\u53ce\u7e2e\u671f\uff09": "120",
        "\u7761\u7720\u6642\u9593": "8",
        "\u4f53\u6e29": "38",
        "\u6d88\u8cbb\u30ab\u30ed\u30ea\u30fc": "300",
        "\u6b69\u6570": "3000",
        "\u6700\u4f4e\u8840\u5727\uff08\u62e1\u5f35\u671f\uff09": "90",
        "\u8840\u4e2d\u9178\u7d20\u6fc3\u5ea6": "95",
        "\u5fc3\u62cd\u6570": "120"
    },
    {
        "\u4f53\u6e29": "38",
        "\u5fc3\u62cd\u6570": "120",
        "\u8840\u4e2d\u9178\u7d20\u6fc3\u5ea6": "95",
        "\u6d88\u8cbb\u30ab\u30ed\u30ea\u30fc": "300",
        "\u6700\u4f4e\u8840\u5727\uff08\u62e1\u5f35\u671f\uff09": "90",
        "\u6700\u9ad8\u8840\u5727\uff08\u53ce\u7e2e\u671f\uff09": "120",
        "\u7761\u7720\u6642\u9593": "8",
        "\u6b69\u6570": "3000"
    },
    {
        "\u8840\u4e2d\u9178\u7d20\u6fc3\u5ea6": "95",
        "\u5fc3\u62cd\u6570": "120",
        "\u6b69\u6570": "3000",
        "\u6700\u9ad8\u8840\u5727\uff08\u53ce\u7e2e\u671f\uff09": "120",
        "\u4f53\u6e29": "38",
        "\u6700\u4f4e\u8840\u5727\uff08\u62e1\u5f35\u671f\uff09": "90",
        "\u7761\u7720\u6642\u9593": "8",
        "\u6d88\u8cbb\u30ab\u30ed\u30ea\u30fc": "300"
    },
    {
        "\u6b69\u6570": "3000",
        "\u6700\u4f4e\u8840\u5727\uff08\u62e1\u5f35\u671f\uff09": "90",
        "\u6700\u9ad8\u8840\u5727\uff08\u53ce\u7e2e\u671f\uff09": "120",
        "\u4f53\u6e29": "38",
        "\u6d88\u8cbb\u30ab\u30ed\u30ea\u30fc": "300",
        "\u7761\u7720\u6642\u9593": "8",
        "\u8840\u4e2d\u9178\u7d20\u6fc3\u5ea6": "95",
        "\u5fc3\u62cd\u6570": "120"
    },
    {
        "exercise_habit": true,
        "diastolic_bp": 90,
        "systolic_bp": 120,
        "sleep_duration": 8,
        "date": "2025-03-19",
        "body_fat": 30,
        "source_type": "direct",
        "user_id": "test_user_1",
        "heart_rate": 120,
        "exercise_kcal": 300,
        "age": 50,
        "body_temperature": 38,
        "steps": 3000,
        "height": 160,
        "weight": 60
    },
    {
        "exercise_habit": true,
        "diastolic_bp": 90,
        "systolic_bp": 120,
        "sleep_duration": 8,
        "date": "2025-03-19",
        "body_fat": 30,
        "source_type": "direct",
        "user_id": "test_user_1",
        "heart_rate": 120,
        "exercise_kcal": 300,
        "age": 50,
        "body_temperature": 38,
        "steps": 3000,
        "height": 160,
        "weight": 60
    },
    {
        "date": "2025-03-19",
        "exercise_kcal": 300,
        "source_type": "direct",
        "age": 50,
        "weight": 60,
        "diastolic_bp": 90,
        "heart_rate": 120,
        "height": 160,
        "sleep_duration": 8,
        "exercise_habit": true,
        "body_fat": 30,
        "steps": 3000,
        "user_id": "test_user_1",
        "systolic_bp": 120,
        "body_temperature": 38
    },
    {
        "\u5fc3\u62cd\u6570": "120",
        "\u6700\u9ad8\u8840\u5727\uff08\u53ce\u7e2e\u671f\uff09": "120",
        "\u8840\u4e2d\u9178\u7d20\u6fc3\u5ea6": "95",
        "\u4f53\u6e29": "38",
        "\u7761\u7720\u6642\u9593": "8",
        "\u6700\u4f4e\u8840\u5727\uff08\u62e1\u5f35\u671f\uff09": "90",
        "\u6b69\u6570": "3000",
        "\u6d88\u8cbb\u30ab\u30ed\u30ea\u30fc": "300"
    },
    {
        "\u5fc3\u62cd\u6570": "120",
        "\u6700\u9ad8\u8840\u5727\uff08\u53ce\u7e2e\u671f\uff09": "120",
        "\u8840\u4e2d\u9178\u7d20\u6fc3\u5ea6": "95",
        "\u4f53\u6e29": "38",
        "\u7761\u7720\u6642\u9593": "8",
        "\u6700\u4f4e\u8840\u5727\uff08\u62e1\u5f35\u671f\uff09": "90",
        "\u6b69\u6570": "3000",
        "\u6d88\u8cbb\u30ab\u30ed\u30ea\u30fc": "300"
    },
    {
        "\u6700\u9ad8\u8840\u5727\uff08\u53ce\u7e2e\u671f\uff09": "120",
        "\u6d88\u8cbb\u30ab\u30ed\u30ea\u30fc": "300",
        "\u5fc3\u62cd\u6570": "120",
        "\u6700\u4f4e\u8840\u5727\uff08\u62e1\u5f35\u671f\uff09": "90",
        "\u6b69\u6570": "3000",
        "\u8840\u4e2d\u9178\u7d20\u6fc3\u5ea6": "95",
        "\u4f53\u6e29": "38",
        "\u7761\u7720\u6642\u9593": "8"
    },
    {
        "\u5fc3\u62cd\u6570": "120",
        "\u6700\u9ad8\u8840\u5727\uff08\u53ce\u7e2e\u671f\uff09": "120",
        "\u8840\u4e2d\u9178\u7d20\u6fc3\u5ea6": "95",
        "\u4f53\u6e29": "38",
        "\u7761\u7720\u6642\u9593": "8",
        "\u6700\u4f4e\u8840\u5727\uff08\u62e1\u5f35\u671f\uff09": "90",
        "\u6b69\u6570": "3000",
        "\u6d88\u8cbb\u30ab\u30ed\u30ea\u30fc": "300"
    },
    {
        "\u5fc3\u62cd\u6570": "120",
        "\u6700\u9ad8\u8840\u5727\uff08\u53ce\u7e2e\u671f\uff09": "120",
        "\u8840\u4e2d\u9178\u7d20\u6fc3\u5ea6": "95",
        "\u4f53\u6e29": "38",
        "\u7761\u7720\u6642\u9593": "8",
        "\u6700\u4f4e\u8840\u5727\uff08\u62e1\u5f35\u671f\uff09": "90",
        "\u6b69\u6570": "3000",
        "\u6d88\u8cbb\u30ab\u30ed\u30ea\u30fc": "300"
    },
    {
        "\u5fc3\u62cd\u6570": "120",
        "\u6700\u9ad8\u8840\u5727\uff08\u53ce\u7e2e\u671f\uff09": "120",
        "\u8840\u4e2d\u9178\u7d20\u6fc3\u5ea6": "95",
        "\u4f53\u6e29": "38",
        "\u7761\u7720\u6642\u9593": "8",
        "\u6700\u4f4e\u8840\u5727\uff08\u62e1\u5f35\u671f\uff09": "90",
        "\u6b69\u6570": "3000",
        "\u6d88\u8cbb\u30ab\u30ed\u30ea\u30fc": "300"
    }
]